python_forecast_utils/__init__.py
python_forecast_utils/sqrt_transformer.py
python_forecast_utils-1.2.0.dist-info/METADATA
python_forecast_utils-1.2.0.dist-info/WHEEL
python_forecast_utils-1.2.0.dist-info/RECORD
