Metadata-Version: 2.1
Name: python_forecast_utils
Version: 1.2.0
Summary: Expose features for python forecast projects
Home-page: https://github.com/lemonde/python-forecast/python-forecast-utils
License: Apache-2.0
Author: Baptiste Geffrault
Author-email: bgeffrault@outlook.fr
Requires-Python: ==3.8.12
Classifier: License :: OSI Approved :: Apache Software License
Classifier: Programming Language :: Python :: 3
Requires-Dist: numpy (==1.23.5)
Requires-Dist: requests (==2.28.2)
Requires-Dist: scikit-learn (==1.0.2)
Project-URL: Repository, https://github.com/lemonde/python-forecast/python-forecast-utils
